setup.py
src/fiveoneseven/__init__.py
src/fiveoneseven/hello.py
src/fiveoneseven.egg-info/PKG-INFO
src/fiveoneseven.egg-info/SOURCES.txt
src/fiveoneseven.egg-info/dependency_links.txt
src/fiveoneseven.egg-info/top_level.txt